asimov_mlx_prompter/__init__.py
asimov_mlx_prompter/__main__.py
asimov_mlx_module-0.0.0.dist-info/METADATA
asimov_mlx_module-0.0.0.dist-info/WHEEL
asimov_mlx_module-0.0.0.dist-info/entry_points.txt
asimov_mlx_module-0.0.0.dist-info/top_level.txt
asimov_mlx_module-0.0.0.dist-info/RECORD
