Metadata-Version: 2.2
Name: asimov-mlx-module
Version: 0.0.0
Summary: ASIMOV MLX Module
Author-email: ASIMOV Protocol <support@asimov.so>
License: Unlicense
Project-URL: Homepage, https://github.com/asimov-modules/asimov-mlx-module
Project-URL: Documentation, https://github.com/asimov-modules/asimov-mlx-module
Project-URL: Repository, https://github.com/asimov-modules/asimov-mlx-module.git
Project-URL: Issues, https://github.com/asimov-modules/asimov-mlx-module/issues
Project-URL: Changelog, https://github.com/asimov-modules/asimov-mlx-module/blob/master/CHANGES.md
Classifier: Development Status :: 2 - Pre-Alpha
Classifier: Environment :: Console
Classifier: Environment :: MacOS X
Classifier: Intended Audience :: Developers
Classifier: License :: OSI Approved :: The Unlicense (Unlicense)
Classifier: Operating System :: MacOS :: MacOS X
Classifier: Programming Language :: Python :: 3
Classifier: Programming Language :: Python :: 3.13
Classifier: Programming Language :: Python :: 3.14
Classifier: Topic :: Scientific/Engineering :: Artificial Intelligence
Classifier: Topic :: Text Processing :: General
Requires-Python: >=3.13
Requires-Dist: mlx>=0.23; sys_platform == "darwin"
Requires-Dist: mlx-lm>=0.21; sys_platform == "darwin"
